krira_augment/__init__.py
krira_augment/client.py
krira_augment/exceptions.py
krira_augment_sdk-1.0.3.dist-info/METADATA
krira_augment_sdk-1.0.3.dist-info/WHEEL
krira_augment_sdk-1.0.3.dist-info/top_level.txt
krira_augment_sdk-1.0.3.dist-info/RECORD
