Metadata-Version: 2.4
Name: krira-augment-sdk
Version: 1.0.3
Summary: Official Python SDK for building integrations with Krira Augment RAG pipelines
Home-page: https://kriralabs.com
Author: Krira Labs
Author-email: support@kriralabs.com
License: MIT
Project-URL: Source, https://github.com/kriralabs/sdk
Project-URL: Tracker, https://github.com/kriralabs/sdk/issues
Classifier: Development Status :: 4 - Beta
Classifier: Intended Audience :: Developers
Classifier: License :: OSI Approved :: MIT License
Classifier: Programming Language :: Python
Classifier: Programming Language :: Python :: 3
Classifier: Programming Language :: Python :: 3.10
Classifier: Programming Language :: Python :: 3.11
Classifier: Programming Language :: Python :: 3.12
Classifier: Topic :: Software Development :: Libraries :: Application Frameworks
Classifier: Topic :: Software Development :: Libraries :: Python Modules
Requires-Python: >=3.9
Requires-Dist: requests<3.0.0,>=2.31.0
Requires-Dist: typing-extensions>=4.0; python_version < "3.11"
Dynamic: author
Dynamic: author-email
Dynamic: classifier
Dynamic: description
Dynamic: description-content-type
Dynamic: home-page
Dynamic: license
Dynamic: project-url
Dynamic: requires-dist
Dynamic: requires-python
Dynamic: summary
